gradinit/__init__.py
gradinit/gradinit.py
gradinit-0.1.1.dist-info/LICENSE
gradinit-0.1.1.dist-info/METADATA
gradinit-0.1.1.dist-info/WHEEL
gradinit-0.1.1.dist-info/top_level.txt
gradinit-0.1.1.dist-info/RECORD
