Metadata-Version: 2.1
Name: gradinit
Version: 0.1.1
Summary: Pytorch implementation of the gradient-based initialization
Home-page: https://github.com/johngull/gradinit
Author: Vitaly Bondar
Author-email: johngull@gmail.com
License: MIT
Platform: UNKNOWN
License-File: LICENSE
Requires-Dist: torch
